LICENSE
MANIFEST.in
README.md
setup.py
docs/man/labelme.1
xllabelme/__init__.py
xllabelme/__main__.py
xllabelme/app.py
xllabelme/label_file.py
xllabelme/logger.py
xllabelme/shape.py
xllabelme/testing.py
xllabelme/ts.py
xllabelme/xlapp.py
xllabelme.egg-info/PKG-INFO
xllabelme.egg-info/SOURCES.txt
xllabelme.egg-info/dependency_links.txt
xllabelme.egg-info/entry_points.txt
xllabelme.egg-info/requires.txt
xllabelme.egg-info/top_level.txt
xllabelme/cli/__init__.py
xllabelme/cli/draw_json.py
xllabelme/cli/draw_label_png.py
xllabelme/cli/json_to_dataset.py
xllabelme/cli/on_docker.py
xllabelme/config/__init__.py
xllabelme/config/default_config.yaml
xllabelme/config/xllabellib.py
xllabelme/icons/cancel.png
xllabelme/icons/close.png
xllabelme/icons/color-line.png
xllabelme/icons/color.png
xllabelme/icons/copy.png
xllabelme/icons/delete.png
xllabelme/icons/done.png
xllabelme/icons/done.svg
xllabelme/icons/edit.png
xllabelme/icons/expert.png
xllabelme/icons/eye.png
xllabelme/icons/feBlend-icon.png
xllabelme/icons/file.png
xllabelme/icons/fit-width.png
xllabelme/icons/fit-window.png
xllabelme/icons/fit.png
xllabelme/icons/help.png
xllabelme/icons/icon.ico
xllabelme/icons/icon.png
xllabelme/icons/icon2.ico
xllabelme/icons/icon2.png
xllabelme/icons/labels.png
xllabelme/icons/labels.svg
xllabelme/icons/new.png
xllabelme/icons/next.png
xllabelme/icons/objects.png
xllabelme/icons/open.png
xllabelme/icons/open.svg
xllabelme/icons/prev.png
xllabelme/icons/quit.png
xllabelme/icons/save-as.png
xllabelme/icons/save-as.svg
xllabelme/icons/save.png
xllabelme/icons/save.svg
xllabelme/icons/undo-cross.png
xllabelme/icons/undo.png
xllabelme/icons/zoom-in.png
xllabelme/icons/zoom-out.png
xllabelme/icons/zoom.png
xllabelme/utils/__init__.py
xllabelme/utils/_io.py
xllabelme/utils/image.py
xllabelme/utils/qt.py
xllabelme/utils/shape.py
xllabelme/widgets/__init__.py
xllabelme/widgets/brightness_contrast_dialog.py
xllabelme/widgets/canvas.py
xllabelme/widgets/color_dialog.py
xllabelme/widgets/escapable_qlist_widget.py
xllabelme/widgets/file_dialog_preview.py
xllabelme/widgets/label_dialog.py
xllabelme/widgets/label_list_widget.py
xllabelme/widgets/tool_bar.py
